{
    "avg": {
        "wmc": 5.93,
        "ccn": 3.22,
        "bugs": 0.11,
        "kanDefect": 0.31,
        "relativeSystemComplexity": 109.68,
        "relativeDataComplexity": 1.71,
        "relativeStructuralComplexity": 107.98,
        "volume": 325.83,
        "commentWeight": 18.82,
        "intelligentContent": 62.93,
        "lcom": 1.61,
        "instability": 0.69,
        "afferentCoupling": 1,
        "efferentCoupling": 2.66,
        "difficulty": 5.45,
        "mi": 76.19,
        "distance": 0.26,
        "incomingCDep": 1.91,
        "incomingPDep": 1.09,
        "outgoingCDep": 4.27,
        "outgoingPDep": 2.82,
        "classesPerPackage": 3.73
    },
    "sum": {
        "loc": 1966,
        "cloc": 319,
        "lloc": 1648,
        "nbMethods": 152,
        "nbClasses": 41,
        "nbInterfaces": 0,
        "nbPackages": 11,
        "violations": {
            "total": 10,
            "information": 0,
            "warning": 8,
            "error": 2,
            "critical": 0
        }
    }
}